{
    "configurations": [
        {
            "name": "Mac",
            "includePath": [
                "${workspaceFolder}/**",
                "${HOME}/.local/include/**"
            ],
            "defines": [],
            "macFrameworkPath": [
                "/Library/Developer/CommandLineTools/SDKs/MacOSX.sdk/System/Library/Frameworks"
            ],
            "compilerPath": "/Users/ts/miniconda3/envs/mpi/bin/mpic++",
            "cStandard": "c17",
            "cppStandard": "c++11",
            "intelliSenseMode": "macos-clang-x64"
        }
    ],
    "version": 4
}